Workbook

Sheet Consolidado
B2: RENDIMIENTO OPERACIONAL 360°
B3: SUCURSAL: | G3: FECHA:
B4: ID | C4: Aspectos Evaluados | D4: Ponderación Global | E4: Peso Relativo | F4: Resultado Evaluación | G4: Puntos Finales por Área | H4: Puntos por Área
B5: TIENDA | D5: 0.35 | E5: 35 | F5: =IF(AND(H5>Parametros!$C$10,H5<Parametros!$D$10),"Critico",IF(AND(H5>Parametros!$C$11,H5<Parametros!$D$11),"Moderado",IF(AND(H5>Parametros!$C$12,H5<=Parametros!$D$12),"Aceptable"))) -> Critico | G5: =SUM(G6:G10) -> 10.9 | H5: =G5/E5 -> 0.31142857
B6: OP | C6: Operaciones - Punto de Venta | D6: 0.25 | E6: 9 | F6: =Petshop!F5 -> Critico | G6: =IF(F6="Aceptable", +(E6*Parametros!$C$7), IF(F6="Moderado", +(E6*Parametros!$C$6), IF(F6="Critico", (E6*Parametros!$C$5)))) -> 2.7
B7: AC | C7: Atencion a Clientes | D7: 0.25 | E7: 9 | F7: =Petshop!F11 -> Critico | G7: =IF(F7="Aceptable", +(E7*Parametros!$C$7), IF(F7="Moderado", +(E7*Parametros!$C$6), IF(F7="Critico", (E7*Parametros!$C$5)))) -> 2.7
B8: GI | C8: Gestion de Inventario | D8: 0.25 | E8: 9 | F8: =Petshop!F17 -> Critico | G8: =IF(F8="Aceptable", +(E8*Parametros!$C$7), IF(F8="Moderado", +(E8*Parametros!$C$6), IF(F8="Critico", (E8*Parametros!$C$5)))) -> 2.7
B9: SL | C9: Seguridad y Limpieza | D9: 0.2 | E9: 7 | F9: =Petshop!F22 -> Critico | G9: =IF(F9="Aceptable", +(E9*Parametros!$C$7), IF(F9="Moderado", +(E9*Parametros!$C$6), IF(F9="Critico", (E9*Parametros!$C$5)))) -> 2.1
B10: AE | C10: Auto-Diagnóstico | D10: 0.05 | E10: 1 | F10: =Petshop!F26 -> Moderado | G10: =IF(F10="Aceptable", +(E10*Parametros!$C$7), IF(F10="Moderado", +(E10*Parametros!$C$6), IF(F10="Critico", (E10*Parametros!$C$5)))) -> 0.7
B11: PELUQUERIA | D11: 0.35 | E11: 35 | F11: =IF(AND(H11>Parametros!$C$10,H11<Parametros!$D$10),"Critico",IF(AND(H11>Parametros!$C$11,H11<Parametros!$D$11),"Moderado",IF(AND(H11>Parametros!$C$12,H11<=Parametros!$D$12),"Aceptable"))) -> Aceptable | G11: =SUM(G12:G15) -> 34.3 | H11: =G11/E11 -> 0.98
B12: BA | C12: Bienestar Animal | D12: 0.45 | E12: 17 | F12: =Grooming!F5 -> Aceptable | G12: =IF(F13="Aceptable", +(E12*Parametros!$C$7), IF(F13="Moderado", +(E12*Parametros!$C$6), IF(F13="Critico", (E12*Parametros!$C$5)))) -> 17
B13: HD | C13: Higiene y Desinfeccion | D13: 0.3 | E13: 10 | F13: =Grooming!F11 -> Aceptable | G13: =IF(F13="Aceptable", +(E13*Parametros!$C$7), IF(F13="Moderado", +(E13*Parametros!$C$6), IF(F13="Critico", (E13*Parametros!$C$5)))) -> 10
B14: PC | C14: Personal Capacitado | D14: 0.2 | E14: 7 | F14: =Grooming!F15 -> Aceptable | G14: =IF(F14="Aceptable", +(E14*Parametros!$C$7), IF(F14="Moderado", +(E14*Parametros!$C$6), IF(F14="Critico", (E14*Parametros!$C$5)))) -> 7
B15: AE | C15: Auto-Diagnóstico | D15: 0.05 | E15: 1 | F15: =Grooming!F18 -> Critico | G15: =IF(F15="Aceptable", +(E15*Parametros!$C$7), IF(F15="Moderado", +(E15*Parametros!$C$6), IF(F15="Critico", (E15*Parametros!$C$5)))) -> 0.3
B16: VETERINARIA | D16: 0.3 | E16: 30 | F16: =IF(AND(H16>Parametros!$C$10,H16<Parametros!$D$10),"Critico",IF(AND(H16>Parametros!$C$11,H16<Parametros!$D$11),"Moderado",IF(AND(H16>Parametros!$C$12,H16<=Parametros!$D$12),"Aceptable"))) -> Aceptable | G16: =SUM(G17:G19) -> 29.3 | H16: =G16/E16 -> 0.97666667
B17: GF | C17: Gestion Farmacológica | D17: 0.475 | E17: 14.5 | F17: =Clinica!F5 -> Aceptable | G17: =IF(F17="Aceptable", +(E17*Parametros!$C$7), IF(F17="Moderado", +(E17*Parametros!$C$6), IF(F17="Critico", (E17*Parametros!$C$5)))) -> 14.5
B18: PR | C18: Procedimiento y Registro Medico | D18: 0.475 | E18: 14.5 | F18: =Clinica!F10 -> Aceptable | G18: =IF(F18="Aceptable", +(E18*Parametros!$C$7), IF(F18="Moderado", +(E18*Parametros!$C$6), IF(F18="Critico", (E18*Parametros!$C$5)))) -> 14.5
B19: AE | C19: Auto-Diagnóstico | D19: 0.05 | E19: 1 | F19: =Clinica!F17 -> Critico | G19: =IF(F19="Aceptable", +(E19*Parametros!$C$7), IF(F19="Moderado", +(E19*Parametros!$C$6), IF(F19="Critico", (E19*Parametros!$C$5)))) -> 0.3
D20: =D5+D11+D16 -> 1 | E20: =E5+E11+E16 -> 100
B21: PORCENTAJE DE CUMPLIMIENTO | G21: =G5+G11+G16 -> 74.5
B23: FIRMA DEL GERENTE
B27: OBSERVACIONES
B28: 1
B29: 2
B30: 3
B31: 4
B32: 5
C34: CALIFICACION GLOBAL POR SUCURSAL | D34: =G21 -> 74.5 | G34: =IF(AND(D34>Parametros!$C$15,D34<=Parametros!$D$15),"DEFICIENTE",IF(AND(D34>Parametros!$C$16,D34<=Parametros!$D$16),"NECESITA MEJORAS",IF(AND(D34>Parametros!$C$17,D34<=Parametros!$D$17),"SATISFACTORIO"))) -> NECESITA MEJORAS
C36: Aceptable
C37: Moderado
C38: Critico

Sheet Petshop
B2: EVALUACIÓN EN TIENDA
B3: SUCURSAL: | D3: GERENTE: | G3: FECHA:
B4: ID | C4: Aspectos Evaluados | D4: Ponderación Global | E4: Peso Relativo | F4: Resultado Evaluación | G4: Puntos Finales por Área | H4: Puntos por Área
B5: OPERACIONES - PUNTO DE VENTA | D5: 0.3 | E5: 30 | F5: =IF(AND(H5>Parametros!$C$10,H5<Parametros!$D$10),"Critico",IF(AND(H5>Parametros!$C$11,H5<Parametros!$D$11),"Moderado",IF(AND(H5>Parametros!$C$12,H5<=Parametros!$D$12),"Aceptable"))) -> Critico | G5: =SUM(G6:G10) -> 9 | H5: =G5/E5 -> 0.3
B6: OP.1 | C6: Se realiza el protocolo de cierre de punto de venta al final del día/turno (arqueo, documentación de vouchers y registro de diferencias). | D6: 0.4 | E6: 13.5 | F6: Critico | G6: =IF(F6="Aceptable", +(E6*Parametros!$C$7), IF(F6="Moderado", +(E6*Parametros!$C$6), IF(F6="Critico", (E6*Parametros!$C$5)))) -> 4.05
B7: OP.2 | C7: Se valida que la venta de medicamentos con receta se realice solo si el cliente presenta el documento, según la ley farmacéutica veterinaria. | D7: 0.3 | E7: 7.5 | F7: Critico | G7: =IF(F7="Aceptable", +(E7*Parametros!$C$7), IF(F7="Moderado", +(E7*Parametros!$C$6), IF(F7="Critico", (E7*Parametros!$C$5)))) -> 2.25
B8: OP.3 | C8: Se mantiene la integridad de precios (el precio marcado en estante o gondola/servicio) cotizado coincide con el precio registrado en el sistema. | D8: 0.1 | E8: 3 | F8: Critico | G8: =IF(F8="Aceptable", +(E8*Parametros!$C$7), IF(F8="Moderado", +(E8*Parametros!$C$6), IF(F8="Critico", (E8*Parametros!$C$5)))) -> 0.9
B9: OP.4 | C9: Se revisa y valida que los descuentos y promociones especiales estén registrados correctamente en el sistema. | D9: 0.1 | E9: 3 | F9: Critico | G9: =IF(F9="Aceptable", +(E9*Parametros!$C$7), IF(F9="Moderado", +(E9*Parametros!$C$6), IF(F9="Critico", (E9*Parametros!$C$5)))) -> 0.9
B10: OP.5 | C10: Se emiten los comprobantes fiscales/facturas electrónicas por cada transacción (productos y servicios). | D10: 0.1 | E10: 3 | F10: Critico | G10: =IF(F10="Aceptable", +(E10*Parametros!$C$7), IF(F10="Moderado", +(E10*Parametros!$C$6), IF(F10="Critico", (E10*Parametros!$C$5)))) -> 0.9
B11: ATENCIÓN A CLIENTES | D11: 0.2 | E11: 20 | F11: =IF(AND(H11>Parametros!$C$10,H11<Parametros!$D$10),"Critico",IF(AND(H11>Parametros!$C$11,H11<Parametros!$D$11),"Moderado",IF(AND(H11>Parametros!$C$12,H11<=Parametros!$D$12),"Aceptable"))) -> Critico | G11: =SUM(G12:G16) -> 6 | H11: =G11/E11 -> 0.3
B12: AC.1 | C12: Se implementa y vive la experiencia de marca "BLACK DOG" con el cliente durante la interacción. | D12: 0.4 | E12: 7 | F12: Critico | G12: =IF(F12="Aceptable", +(E12*Parametros!$C$7), IF(F12="Moderado", +(E12*Parametros!$C$6), IF(F12="Critico", (E12*Parametros!$C$5)))) -> 2.1
B13: AC.2 | C13: El personal está capacitado para proporcionar la información correcta sobre cada producto (dieta, cuidado, hábitat). | D13: 0.3 | E13: 5 | F13: Critico | G13: =IF(F13="Aceptable", +(E13*Parametros!$C$7), IF(F13="Moderado", +(E13*Parametros!$C$6), IF(F13="Critico", (E13*Parametros!$C$5)))) -> 1.5
B14: AC.3 | C14: Se registran y gestionan de forma protocolaria las quejas o incidentes de clientes. | D14: 0.2 | E14: 4 | F14: Critico | G14: =IF(F14="Aceptable", +(E14*Parametros!$C$7), IF(F14="Moderado", +(E14*Parametros!$C$6), IF(F14="Critico", (E14*Parametros!$C$5)))) -> 1.2
B15: AC.4 | C15: Se Le envian fotos a los clientes al final de cada servicio realizado en el area de Grooming | D15: 0.05 | E15: 2 | F15: Critico | G15: =IF(F15="Aceptable", +(E15*Parametros!$C$7), IF(F15="Moderado", +(E15*Parametros!$C$6), IF(F15="Critico", (E15*Parametros!$C$5)))) -> 0.6
B16: AC.5 | C16: Se ofrece una despedida profesional al cliente (se agradece la compra/servicio) y se confirma si desea agendar algún servicio adicional (próxima cita, grooming). | D16: 0.05 | E16: 2 | F16: Critico | G16: =IF(F16="Aceptable", +(E16*Parametros!$C$7), IF(F16="Moderado", +(E16*Parametros!$C$6), IF(F16="Critico", (E16*Parametros!$C$5)))) -> 0.6
B17: GESTIÓN DE INVENTARIO | D17: 0.3 | E17: 30 | F17: =IF(AND(H17>Parametros!$C$10,H17<Parametros!$D$10),"Critico",IF(AND(H17>Parametros!$C$11,H17<Parametros!$D$11),"Moderado",IF(AND(H17>Parametros!$C$12,H17<=Parametros!$D$12),"Aceptable"))) -> Critico | G17: =SUM(G18:G21) -> 9 | H17: =G17/E17 -> 0.3
B18: GI.1 | C18: Realizan bisemanalmente un control riguroso de la fecha de vencimiento de los alimentos, snacks y los medicamentos de venta libre. | D18: 0.45 | E18: 15 | F18: Critico | G18: =IF(F18="Aceptable", +(E18*Parametros!$C$7), IF(F18="Moderado", +(E18*Parametros!$C$6), IF(F18="Critico", (E18*Parametros!$C$5)))) -> 4.5
B19: GI.2 | C19: Sistema FEFO aplicado a medicamentos y alimentos perecederos para la rotación de stock y prevención de pérdidas. | D19: 0.3 | E19: 10 | F19: Critico | G19: =IF(F19="Aceptable", +(E19*Parametros!$C$7), IF(F19="Moderado", +(E19*Parametros!$C$6), IF(F19="Critico", (E19*Parametros!$C$5)))) -> 3
B20: GI.3 | C20: Se solicita la dotación de mercancía baja en stock (requisición) previo a quedarse sin ella, asegurando un flujo constante de inventario. | D20: 0.15 | E20: 3 | F20: Critico | G20: =IF(F20="Aceptable", +(E20*Parametros!$C$7), IF(F20="Moderado", +(E20*Parametros!$C$6), IF(F20="Critico", (E20*Parametros!$C$5)))) -> 0.9
B21: GI.4 | C21: Cuentan con un espacio de almacenamiento dentro de las instalaciones para los alimentos no exibidos (evitando plaga, humedad o calor excesivo). | D21: 0.1 | E21: 2 | F21: Critico | G21: =IF(F21="Aceptable", +(E21*Parametros!$C$7), IF(F21="Moderado", +(E21*Parametros!$C$6), IF(F21="Critico", (E21*Parametros!$C$5)))) -> 0.6
B22: SEGURIDAD Y LIMPIEZA | D22: 0.15 | E22: 15 | F22: =IF(AND(H22>Parametros!$C$10,H22<Parametros!$D$10),"Critico",IF(AND(H22>Parametros!$C$11,H22<Parametros!$D$11),"Moderado",IF(AND(H22>Parametros!$C$12,H22<=Parametros!$D$12),"Aceptable"))) -> Critico | G22: =SUM(G23:G25) -> 4.5 | H22: =G22/E22 -> 0.3
B23: SL.1 | C23: Las estanterías y exhibidores se encuentran organizadas, limpias y surtidas adecuadamente con el stock existente. | D23: 0.4 | E23: 8 | F23: Critico | G23: =IF(F23="Aceptable", +(E23*Parametros!$C$7), IF(F23="Moderado", +(E23*Parametros!$C$6), IF(F23="Critico", (E23*Parametros!$C$5)))) -> 2.4
B24: SL.2 | C24: Los productos pesados o voluminosos están colocados en lugares estables y bajos, evitando riesgos de caída o accidentes. | D24: 0.3 | E24: 5 | F24: Critico | G24: =IF(F24="Aceptable", +(E24*Parametros!$C$7), IF(F24="Moderado", +(E24*Parametros!$C$6), IF(F24="Critico", (E24*Parametros!$C$5)))) -> 1.5
B25: SL.3 | C25: Se realiza diariamente la limpieza general de las áreas clave (comedor/descanso, baños, peluquería, piso de venta) y se mantiene un control efectivo de olores dentro de la tienda, especialmente en las áreas cercanas a servicios o alimento. | D25: 0.2 | E25: 2 | F25: Critico | G25: =IF(F25="Aceptable", +(E25*Parametros!$C$7), IF(F25="Moderado", +(E25*Parametros!$C$6), IF(F25="Critico", (E25*Parametros!$C$5)))) -> 0.6
B26: AUTO-DIAGNÓSTICO | D26: 0.05 | E26: 5 | F26: =IF(AND(H26>Parametros!$C$10,H26<Parametros!$D$10),"Critico",IF(AND(H26>Parametros!$C$11,H26<Parametros!$D$11),"Moderado",IF(AND(H26>Parametros!$C$12,H26<=Parametros!$D$12),"Aceptable"))) -> Moderado | G26: =SUM(G27) -> 3.5 | H26: =G26/E26 -> 0.7
B27: AE.1 | C27: revisión objetiva y honesta del nivel de cumplimiento y riesgo dentro de sus procesos operacionales | D27: 1 | E27: 5 | F27: Moderado | G27: =IF(F27="Aceptable", +(E27*Parametros!$C$7), IF(F27="Moderado", +(E27*Parametros!$C$6), IF(F27="Critico", (E27*Parametros!$C$5)))) -> 3.5
D28: =D5+D11+D17+D22+D26 -> 1 | E28: =E5+E11+E17+E22+E26 -> 100
B29: PORCENTAJE DE CUMPLIMIENTO | G29: =G5+G11+G17+G22 -> 28.5
B31: FIRMA DEL GERENTE
B35: OBSERVACIONES
B36: 1
B37: 2
B38: 3
B39: 4
B40: 5
C42: CALIFICACION SUCURSAL | D42: =G29 -> 28.5 | G42: =IF(AND(D42>Parametros!$C$15,D42<=Parametros!$D$15),"DEFICIENTE",IF(AND(D42>Parametros!$C$16,D42<=Parametros!$D$16),"NECESITA MEJORAS",IF(AND(D42>Parametros!$C$17,D42<=Parametros!$D$17),"SATISFACTORIO"))) -> DEFICIENTE
C44: Aceptable
C45: Moderado
C46: Critico

Sheet Grooming
B2: EVALUACIÓN EN PELUQUERIA
B3: SUCURSAL: | D3: FECHA:
B4: ID | C4: Aspectos Evaluados | D4: Ponderación Global | E4: Peso Relativo | F4: Resultado Evaluación | G4: Puntos Finales por Área | H4: Puntos por Área
B5: BIENESTAR ANIMAL | D5: 0.45 | E5: 45 | F5: =IF(AND(H5>Parametros!$C$10,H5<Parametros!$D$10),"Critico",IF(AND(H5>Parametros!$C$11,H5<Parametros!$D$11),"Moderado",IF(AND(H5>Parametros!$C$12,H5<=Parametros!$D$12),"Aceptable"))) -> Aceptable | G5: =SUM(G6:G10) -> 45 | H5: =G5/E5 -> 1
B6: BA.1 | C6: Se mantiene un protocolo de manejo de animales nerviosos o agresivos | D6: 0.35 | E6: 13 | F6: Aceptable | G6: =IF(F6="Aceptable", +(E6*Parametros!$C$7), IF(F6="Moderado", +(E6*Parametros!$C$6), IF(F6="Critico", (E6*Parametros!$C$5)))) -> 13
B7: BA.2 | C7: Utilizan equipos de sujecion seguros y adecuados para cada servicio. | D7: 0.2 | E7: 10 | F7: Aceptable | G7: =IF(F7="Aceptable", +(E7*Parametros!$C$7), IF(F7="Moderado", +(E7*Parametros!$C$6), IF(F7="Critico", (E7*Parametros!$C$5)))) -> 10
B8: BA.3 | C8: Nunca dejan a los animales solos en las bañeras o en las mesas de forma insegura. | D8: 0.2 | E8: 10 | F8: Aceptable | G8: =IF(F8="Aceptable", +(E8*Parametros!$C$7), IF(F8="Moderado", +(E8*Parametros!$C$6), IF(F8="Critico", (E8*Parametros!$C$5)))) -> 10
B9: BA.3 | C9: Se realiza el triage en la peluqueria para conocer problemas de piel, alergias, etc. | D9: 0.15 | E9: 7 | F9: Aceptable | G9: =IF(F9="Aceptable", +(E9*Parametros!$C$7), IF(F9="Moderado", +(E9*Parametros!$C$6), IF(F9="Critico", (E9*Parametros!$C$5)))) -> 7
B10: BA.4 | C10: Todas las jaulas mantienen sus comanda y un correcto cronograma, monitoreando el tiempo máximo de espera y permanencia de los animales. | D10: 0.1 | E10: 5 | F10: Aceptable | G10: =IF(F10="Aceptable", +(E10*Parametros!$C$7), IF(F10="Moderado", +(E10*Parametros!$C$6), IF(F10="Critico", (E10*Parametros!$C$5)))) -> 5
B11: HIGIENE Y DESINFECCION | D11: 0.3 | E11: 30 | F11: =IF(AND(H11>Parametros!$C$10,H11<Parametros!$D$10),"Critico",IF(AND(H11>Parametros!$C$11,H11<Parametros!$D$11),"Moderado",IF(AND(H11>Parametros!$C$12,H11<=Parametros!$D$12),"Aceptable"))) -> Aceptable | G11: =SUM(G12:G14) -> 30 | H11: =G11/E11 -> 1
B12: HD.1 | C12: Realizan la limpieza y desinfección de las herramientas (tijeras, cuchillas, cepillos) entre un animal y otro para prevenir la transmisión de parásitos o enfermedades de la piel. | D12: 0.4 | E12: 12.5 | F12: Aceptable | G12: =IF(F12="Aceptable", +(E12*Parametros!$C$7), IF(F12="Moderado", +(E12*Parametros!$C$6), IF(F12="Critico", (E12*Parametros!$C$5)))) -> 12.5
B13: HD.2 | C13: Mantienen una limpieza diaria de bañeras, mesas y suelo en el area de trabajo. | D13: 0.3 | E13: 10 | F13: Aceptable | G13: =IF(F13="Aceptable", +(E13*Parametros!$C$7), IF(F13="Moderado", +(E13*Parametros!$C$6), IF(F13="Critico", (E13*Parametros!$C$5)))) -> 10
B14: HD.3 | C14: Utilizan los productos (champús, acondicionadores) de grado profesional y adecuados para cada tipo de piel/pelaje. | D14: 0.2 | E14: 7.5 | F14: Aceptable | G14: =IF(F14="Aceptable", +(E14*Parametros!$C$7), IF(F14="Moderado", +(E14*Parametros!$C$6), IF(F14="Critico", (E14*Parametros!$C$5)))) -> 7.5
B15: PERSONAL CAPACITADO | D15: 0.2 | E15: 20 | F15: =IF(AND(H15>Parametros!$C$10,H15<Parametros!$D$10),"Critico",IF(AND(H15>Parametros!$C$11,H15<Parametros!$D$11),"Moderado",IF(AND(H15>Parametros!$C$12,H15<=Parametros!$D$12),"Aceptable"))) -> Aceptable | G15: =SUM(G16:G17) -> 20 | H15: =G15/E15 -> 1
B16: PC.1 | C16: Se cuenta con el personal capacitado o con experiencia en peluqueria | D16: 0.5 | E16: 14.5 | F16: Aceptable | G16: =IF(F16="Aceptable", +(E16*Parametros!$C$7), IF(F16="Moderado", +(E16*Parametros!$C$6), IF(F16="Critico", (E16*Parametros!$C$5)))) -> 14.5
B17: PC.2 | C17: Este personal cuenta con conocimientos basicos en primeros auxilios para mascotas | D17: 0.3 | E17: 5.5 | F17: Aceptable | G17: =IF(F17="Aceptable", +(E17*Parametros!$C$7), IF(F17="Moderado", +(E17*Parametros!$C$6), IF(F17="Critico", (E17*Parametros!$C$5)))) -> 5.5
B18: AUTO-DIAGNÓSTICO | D18: 0.05 | E18: 5 | F18: =IF(AND(H18>Parametros!$C$10,H18<Parametros!$D$10),"Critico",IF(AND(H18>Parametros!$C$11,H18<Parametros!$D$11),"Moderado",IF(AND(H18>Parametros!$C$12,H18<=Parametros!$D$12),"Aceptable"))) -> Critico | G18: =SUM(G19) -> 1.5 | H18: =G18/E18 -> 0.3
B19: AE.1 | C19: revisión objetiva y honesta del nivel de cumplimiento y riesgo dentro de sus procesos operacionales | D19: 1 | E19: 5 | F19: Critico | G19: =IF(F19="Aceptable", +(E19*Parametros!$C$7), IF(F19="Moderado", +(E19*Parametros!$C$6), IF(F19="Critico", (E19*Parametros!$C$5)))) -> 1.5
D20: =D5+D11+D15+D18 -> 1 | E20: =E5+E11+E15+E18 -> 100
B21: PORCENTAJE DE CUMPLIMIENTO | G21: =G5+G11+G15 -> 95
B23: FIRMA DEL GERENTE
B27: OBSERVACIONES
B28: 1
B29: 2
B30: 3
B31: 4
B32: 5
C35: CALIFICACION SUCURSAL | D35: =G21 -> 95 | G35: =IF(AND(D35>Parametros!$C$15,D35<=Parametros!$D$15),"DEFICIENTE",IF(AND(D35>Parametros!$C$16,D35<=Parametros!$D$16),"NECESITA MEJORAS",IF(AND(D35>Parametros!$C$17,D35<=Parametros!$D$17),"SATISFACTORIO"))) -> SATISFACTORIO
C36: Aceptable
C37: Moderado
C38: Critico

Sheet Clinica
B2: EVALUACIÓN EN VETERINARIA
B3: SUCURSAL: | D3: DOCTOR: | G3: FECHA:
B4: ID | C4: Aspectos Evaluados | D4: Ponderación Global | E4: Peso Relativo | F4: Resultado Evaluación | G4: Puntos Finales por Área | H4: Puntos por Área
B5: GESTION FARMACOLÓGICA | D5: 0.475 | E5: =SUM(E6:E9) -> 47.5 | F5: =IF(AND(H5>Parametros!$C$10,H5<Parametros!$D$10),"Critico",IF(AND(H5>Parametros!$C$11,H5<Parametros!$D$11),"Moderado",IF(AND(H5>Parametros!$C$12,H5<=Parametros!$D$12),"Aceptable"))) -> Aceptable | G5: =SUM(G6:G9) -> 47.5 | H5: =G5/E5 -> 1
B6: GF.1 | C6: Realiza el uso obligatorio de Equipo de Protección Personal adecuado para cada procedimiento (guantes desechables, batas, mascarillas, gafas/protectores faciales). | D6: 0.4 | E6: 14 | F6: Aceptable | G6: =IF(F6="Aceptable", +(E6*Parametros!$C$7), IF(F6="Moderado", +(E6*Parametros!$C$6), IF(F6="Critico", (E6*Parametros!$C$5)))) -> 14
B7: GF.2 | C7: Protocolo de manejo y desecho adecuado de material punzocortante y residuos biológicos (RPBI/Residuos peligrosos). | D7: 0.4 | E7: 14 | F7: Aceptable | G7: =IF(F7="Aceptable", +(E7*Parametros!$C$7), IF(F7="Moderado", +(E7*Parametros!$C$6), IF(F7="Critico", (E7*Parametros!$C$5)))) -> 14
B8: GF.3 | C8: Se mantiene un debido control y registro de medicamentos restringidos En caso de aplicar. | D8: 0.1 | E8: 10 | F8: Aceptable | G8: =IF(F8="Aceptable", +(E8*Parametros!$C$7), IF(F8="Moderado", +(E8*Parametros!$C$6), IF(F8="Critico", (E8*Parametros!$C$5)))) -> 10
B9: GF.4 | C9: Se verifica la cadena de frío para vacunas y medicamentos termolábiles (registro de temperaturas). | D9: 0.1 | E9: 9.5 | F9: Aceptable | G9: =IF(F9="Aceptable", +(E9*Parametros!$C$7), IF(F9="Moderado", +(E9*Parametros!$C$6), IF(F9="Critico", (E9*Parametros!$C$5)))) -> 9.5
B10: PROCEDIMIENTO Y REGISTRO MÉDICO | D10: 0.475 | E10: =SUM(E11:E16) -> 47.5 | F10: =IF(AND(H10>Parametros!$C$10,H10<Parametros!$D$10),"Critico",IF(AND(H10>Parametros!$C$11,H10<Parametros!$D$11),"Moderado",IF(AND(H10>Parametros!$C$12,H10<=Parametros!$D$12),"Aceptable"))) -> Aceptable | G10: =SUM(G11:G16) -> 47.5 | H10: =G10/E10 -> 1
B11: PR.1 | C11: Realiza la revisión de la historia clínica de los pacientes (legibilidad, firma del veterinario, consentimiento informado para cirugías cuando aplique. | D11: 0.25 | E11: 12 | F11: Aceptable | G11: =IF(F11="Aceptable", +(E11*Parametros!$C$7), IF(F11="Moderado", +(E11*Parametros!$C$6), IF(F11="Critico", (E11*Parametros!$C$5)))) -> 12
B12: PR.2 | C12: El HC incluye la identificación completa del propietario, anamnesis o entrevista al propietario, diagnóstico, plan de tratamiento y seguimiento. | D12: 0.25 | E12: 12 | F12: Aceptable | G12: =IF(F12="Aceptable", +(E12*Parametros!$C$7), IF(F12="Moderado", +(E12*Parametros!$C$6), IF(F12="Critico", (E12*Parametros!$C$5)))) -> 12
B13: PR.3 | C13: Se realiza la verificación de los protocolos de comunicación de resultados y el estado de los pacientes a los propietarios (sistema de llamadas o updates). | D13: 0.25 | E13: 12 | F13: Aceptable | G13: =IF(F13="Aceptable", +(E13*Parametros!$C$7), IF(F13="Moderado", +(E13*Parametros!$C$6), IF(F13="Critico", (E13*Parametros!$C$5)))) -> 12
B14: PR.4 | C14: Realiza la revision de disponibilidad y mantenimiento de equipos (laboratorio, anestesia, rayos X, etc.). | D14: 0.1 | E14: 5 | F14: Aceptable | G14: =IF(F14="Aceptable", +(E14*Parametros!$C$7), IF(F14="Moderado", +(E14*Parametros!$C$6), IF(F14="Critico", (E14*Parametros!$C$5)))) -> 5
B15: PR.5 | C15: Mantiene un protocolos de limpieza y esterilización del instrumental quirúrgico y de consulta. | D15: 0.1 | E15: 5 | F15: Aceptable | G15: =IF(F15="Aceptable", +(E15*Parametros!$C$7), IF(F15="Moderado", +(E15*Parametros!$C$6), IF(F15="Critico", (E15*Parametros!$C$5)))) -> 5
B16: PR.6 | C16: Mantiene un protocolo de desinfección entre pacientes en mesas de consulta, jaulas y áreas comunes. | D16: 0.05 | E16: 1.5 | F16: Aceptable | G16: =IF(F16="Aceptable", +(E16*Parametros!$C$7), IF(F16="Moderado", +(E16*Parametros!$C$6), IF(F16="Critico", (E16*Parametros!$C$5)))) -> 1.5
B17: AUTO-DIAGNÓSTICO | D17: 0.05 | E17: =E18 -> 5 | F17: =IF(AND(H17>Parametros!$C$10,H17<Parametros!$D$10),"Critico",IF(AND(H17>Parametros!$C$11,H17<Parametros!$D$11),"Moderado",IF(AND(H17>Parametros!$C$12,H17<=Parametros!$D$12),"Aceptable"))) -> Critico | G17: =SUM(G18) -> 1.5 | H17: =G17/E17 -> 0.3
B18: AE.1 | C18: revisión objetiva y honesta del nivel de cumplimiento y riesgo dentro de sus procesos operacionales | D18: 1 | E18: 5 | F18: Critico | G18: =IF(F18="Aceptable", +(E18*Parametros!$C$7), IF(F18="Moderado", +(E18*Parametros!$C$6), IF(F18="Critico", (E18*Parametros!$C$5)))) -> 1.5
D19: =D5+D10+D17 -> 1 | E19: =E5+E10+E17 -> 100
B20: PORCENTAJE DE CUMPLIMIENTO | G20: =G5+G10 -> 95
B22: FIRMA DEL GERENTE
B26: OBSERVACIONES
B27: 1
B28: 2
B29: 3
B30: 4
B31: 5
C34: CALIFICACION SUCURSAL | D34: =G20 -> 95 | G34: =IF(AND(D34>Parametros!$C$15,D34<=Parametros!$D$15),"DEFICIENTE",IF(AND(D34>Parametros!$C$16,D34<=Parametros!$D$16),"NECESITA MEJORAS",IF(AND(D34>Parametros!$C$17,D34<=Parametros!$D$17),"SATISFACTORIO"))) -> SATISFACTORIO
C35: Aceptable
C36: Moderado
C37: Critico

Sheet Parametros
B4: CALIFICACIÓN ÁREA | C4: MULTIPLICADOR
B5: Critico | C5: 0.3
B6: Moderado | C6: 0.7
B7: Aceptable | C7: 1
B9: CALIFICACIÓN ASPECTO EVALUADO | C9: Min | D9: Max
B10: Critico | C10: 0.01 | D10: 0.6
B11: Moderado | C11: 0.61 | D11: 0.8
B12: Aceptable | C12: 0.81 | D12: 1
B14: CALIFICACIÓN GLOBAL | C14: Min | D14: Max
B15: Deficiente | C15: 1 | D15: 40
B16: Necesita Mejoras | C16: 41 | D16: 80
B17: Satisfactorio | C17: 81 | D17: 100

Sheet Riesgo
B9: Nivel de Calificación | C9: Definición del Riesgo | D9: Planificacion
A10: NIVEL DE RIESGO | B10: Crítico | C10: Riesgo Alto Fallas mayores en controles clave, incumplimiento de regulaciones esenciales, o debilidades que exponen a la organización a un daño significativo (pérdidas financieras sustanciales, interrupción de servicios, multas o daño reputacional grave). | D10: Se requiere un plan de acción urgente y un seguimiento constante.
B11: Moderado | C11: Riesgo Medio Deficiencias en controles secundarios o inconsistencias significativas en la ejecución del proceso. El impacto potencial es material, pero no catastrófico (errores frecuentes, ineficiencias notables, o incumplimiento parcial de políticas internas). | D11: Se requiere un plan de acción documentado con plazos definidos y asignación de responsables.
B12: Aceptable | C12: Riesgo Bajo El proceso opera generalmente bien, con controles clave funcionando. Los hallazgos son menores o son Oportunidades de Mejora (ineficiencias leves, errores aislados, o mejoras sugeridas para optimizar el rendimiento). | D12: Se requiere registrar los ciclos normales de mejora continua.
